unique_swot/__init__.py
unique_swot/config.py
unique_swot/docs/README.md
unique_swot/docs/architecture.md
unique_swot/docs/complete_workflow.md
unique_swot/docs/generation.md
unique_swot/docs/reporting.md
unique_swot/docs/source_management.md
unique_swot/docs/supporting_services.md
unique_swot/service.py
unique_swot/services/citations.py
unique_swot/services/generation/agentic/agent.py
unique_swot/services/generation/agentic/commands.py
unique_swot/services/generation/agentic/config.py
unique_swot/services/generation/agentic/exceptions.py
unique_swot/services/generation/agentic/executor.py
unique_swot/services/generation/agentic/operations.py
unique_swot/services/generation/agentic/prompts/commands/config.py
unique_swot/services/generation/agentic/prompts/commands/create_new_section/config.py
unique_swot/services/generation/agentic/prompts/commands/create_new_section/system_prompt.j2
unique_swot/services/generation/agentic/prompts/commands/create_new_section/user_prompt.j2
unique_swot/services/generation/agentic/prompts/commands/update_existing_section/config.py
unique_swot/services/generation/agentic/prompts/commands/update_existing_section/system_prompt.j2
unique_swot/services/generation/agentic/prompts/commands/update_existing_section/user_prompt.j2
unique_swot/services/generation/agentic/prompts/config.py
unique_swot/services/generation/agentic/prompts/definition/config.py
unique_swot/services/generation/agentic/prompts/extraction/config.py
unique_swot/services/generation/agentic/prompts/extraction/system_prompt.j2
unique_swot/services/generation/agentic/prompts/extraction/user_prompt.j2
unique_swot/services/generation/agentic/prompts/plan/config.py
unique_swot/services/generation/agentic/prompts/plan/system_prompt.j2
unique_swot/services/generation/agentic/prompts/plan/user_prompt.j2
unique_swot/services/generation/agentic/utils.py
unique_swot/services/generation/config.py
unique_swot/services/generation/context.py
unique_swot-1.2.3.dist-info/LICENSE
unique_swot-1.2.3.dist-info/METADATA
unique_swot-1.2.3.dist-info/WHEEL
unique_swot-1.2.3.dist-info/RECORD
