Metadata-Version: 2.1
Name: unique-swot
Version: 1.2.3
Summary: Unique Swot package is a tool that for conducting a swot analysis based on internal and external documents
License: Proprietary
Author: Rami Azouz
Author-email: rami.ext@unique.ch
Requires-Python: >=3.12,<4.0
Classifier: License :: Other/Proprietary License
Classifier: Programming Language :: Python :: 3
Classifier: Programming Language :: Python :: 3.12
Requires-Dist: jinja2 (>=3.1.0,<4.0.0)
Requires-Dist: pydantic (>=2.8.2,<3.0.0)
Requires-Dist: tiktoken (>=0.12.0,<0.13.0)
Requires-Dist: tqdm (>=4.66.0,<5.0.0)
Requires-Dist: typing-extensions (>=4.9.0,<5.0.0)
Requires-Dist: unique-quartr (>=0.2.1,<0.3.0)
Requires-Dist: unique-toolkit (>=1.38.1,<2.0.0)
